badapple/__init__.py
badapple/__main__.py
badapple/audio.py
badapple/badapple.badapple
badapple/badapple.mp3
badapple/badapple.mp4
badapple/badapple.wav
badapple/builtin_files.py
badapple/color.py
badapple/consola_ascii_0_ff.data
badapple/play.py
badapple/replay.py
badapple/util.py
badapple-0.0.8.dist-info/LICENSE
badapple-0.0.8.dist-info/METADATA
badapple-0.0.8.dist-info/WHEEL
badapple-0.0.8.dist-info/top_level.txt
badapple-0.0.8.dist-info/RECORD
