Metadata-Version: 2.1
Name: badapple
Version: 0.0.8
Summary: play the video in the console as ASCII art
Author-email: userElaina <userelaina@pm.me>
Maintainer-email: userElaina <userelaina@pm.me>
License: MIT License
Project-URL: Homepage, https://github.com/bad-apple-lab/Bad-Apple-Python-Module
Project-URL: Bug Reports, https://github.com/bad-apple-lab/Bad-Apple-Python-Module/issues
Project-URL: Source, https://github.com/bad-apple-lab/Bad-Apple-Python-Module
Keywords: badapple,asciiart
Classifier: License :: OSI Approved :: MIT License
Classifier: Programming Language :: Python :: 3
Requires-Python: >=3.7
License-File: LICENSE
Requires-Dist: opencv-python
Provides-Extra: anyplayer
Requires-Dist: anyplayer >=0.0.5 ; extra == 'anyplayer'
Provides-Extra: audio
Requires-Dist: anyplayer >=0.0.5 ; extra == 'audio'
Provides-Extra: dev
Requires-Dist: anyplayer[dev] >=0.0.5 ; extra == 'dev'
Requires-Dist: x256offline >=0.0.3 ; extra == 'dev'
Provides-Extra: playsound
Requires-Dist: anyplayer[playsound] >=0.0.5 ; extra == 'playsound'
Provides-Extra: pyaudio
Requires-Dist: anyplayer[pyaudio] >=0.0.5 ; extra == 'pyaudio'
Provides-Extra: simpleaudio
Requires-Dist: anyplayer[simpleaudio] >=0.0.5 ; extra == 'simpleaudio'
Provides-Extra: x256
Requires-Dist: x256offline >=0.0.3 ; extra == 'x256'
